devolv/__init__.py
devolv/cli.py
devolv/drift/__init__.py
devolv/drift/aws_fetcher.py
devolv/drift/cli.py
devolv/drift/comparator.py
devolv/drift/file_loader.py
devolv/drift/github_approvals.py
devolv/drift/issues.py
devolv/drift/report.py
devolv/drift/utils.py
devolv/iam/__init__.py
devolv/iam/validator/__init__.py
devolv/iam/validator/cli.py
devolv/iam/validator/core.py
devolv/iam/validator/folder.py
devolv/iam/validator/rules.py
devolv-0.2.40.dist-info/licenses/LICENSE
devolv-0.2.40.dist-info/METADATA
devolv-0.2.40.dist-info/WHEEL
devolv-0.2.40.dist-info/entry_points.txt
devolv-0.2.40.dist-info/top_level.txt
devolv-0.2.40.dist-info/RECORD
