Metadata-Version: 2.4
Name: devolv
Version: 0.2.40
Summary: Modular DevOps Toolkit with IAM policy validation
Author-email: Devolv Dev <devolv.dev@gmail.com>
License-Expression: MIT
Requires-Python: >=3.8
License-File: LICENSE
Requires-Dist: typer>=0.9
Requires-Dist: PyYAML
Requires-Dist: deepdiff>=6.0.0
Requires-Dist: boto3
Requires-Dist: PyGithub
Provides-Extra: dev
Requires-Dist: pytest; extra == "dev"
Requires-Dist: pytest-cov; extra == "dev"
Requires-Dist: coverage-badge; extra == "dev"
Requires-Dist: rich; extra == "dev"
Dynamic: license-file
